[
  {
    "number": "ุฒูุฌุฉ ุขุฏู ุนููู ุงูุณูุงู ",
    "text": "",
    "label": "ุขุฏู ุนููู ุงูุณูุงู :\n ุฒูุฌุชู ูู ุงูุณูุฏุฉ ุญูุงุก ู ูุฏ ุฎูููุช ูู ุถูุน ุขุฏู ุนููู ุงูุณูุงู ."
  },
  {
    "number": "ุฒูุฌุฉ ุดูุซ ุนููู ุงูุณูุงู ",
    "text": "",
    "label": "ุดูุซ ุนููู ุงูุณูุงู :\nููุงู ุฃู ุดูุซ ุนููู ุงูุณูุงู ูู ุซุงูุซ ุฃุจูุงุก ุขุฏู ู ุญูุงุก .\nุฐูุฑ ุจุนุถ ุงูุณูู ุฃู ุฒูุฌุฉ ุงููุจู ุดูุซ ูู ุฃุฒูุฑุง .                      "
  },
  {
    "number": "ุฒูุฌุฉ ููุญ ุนููู ุงูุณูุงู ",
    "text": "",
    "label": "ููุญ ุนููู ุงูุณูุงู :\n ุฒูุฌุฉ ูุจู ุงููู ููุญ ุนููู ุงูุณูุงู ูู ูุงูุบุฉ ."
  },
  {
    "number": "ุฒูุฌุฉ ููุฏ ุนููู ุงูุณูุงู ",
    "text": "",
    "label": "\nููุฏ ุนููู ุงูุณูุงู :\nููุฏ ูุงู ุนููู ุงูุณูุงู ุฃุญุฏ ุงูุฃูุจูุงุก ุงูุนุฑุจ ุ ูููุงู ุฃู ุงุณู ุฒูุฌุฉ ุงููุจู ููุฏ ุนููู ุงูุณูุงู ูู ุนุฑูุฉ .                      "
  },
  {
    "number": "ุฒูุฌุฉ ุฅุจุฑุงููู ุนููู ุงูุณูุงู ",
    "text": "",
    "label": "ุฅุจุฑุงููู ุนููู ุงูุณูุงู :\nุชุฒูุฌ ูุจู ุงููู ุฅุจุฑุงููู ุนููู ุงูุณูุงู ุจุงูุณูุฏุฉ ุณุงุฑุฉ ุจูุช ูุงุฑุงู ุงุจูู ุนูู ุซู ุชุฒูุฌ ูู ุงูุณูุฏุฉ ูุงุฌุฑ ุงููุตุฑูุฉ.\nุชุฒูุฌ ุจุนุฏูุง ุนููู ุงูุณูุงู ูู ูุทูุฑุฉ  ุฃู ููุทูุฑุง ุจูุช ููุทู ุงูููุนุงููุฉ ุจุนุฏ ููุงุฉ ุฒูุฌุชูู ุณุงุฑุฉ ู ูุงุฌุฑ .\nุซู ุชุฒูุฌ ุนููู ุงูุณูุงู ูู ุญุฌูู ุจูุช ุฃููู ุจุนุฏ ุฒูุฌุชู ููุทูุฑุฉ ."
  },
  {
    "number": "ุฒูุฌุฉ ููุท ุนููู ุงูุณูุงู ",
    "text": "",
    "label": " ููุท ุนููู ุงูุณูุงู :\nุฒูุฌุฉ  ุงููุจู ููุท ุนููู ุงูุณูุงู ุงุณููุง ูุงููุฉ ู ููู ูุงูุนุฉ ."
  },
  {
    "number": "ุฒูุฌุฉ ุฅุณูุงุนูู ุนููู ุงูุณูุงู ",
    "text": "",
    "label": "ุฅุณูุงุนูู ุนููู ุงูุณูุงู :\nุชุฒูุฌ ุฅุณูุงุนูู ุนููู ุงูุณูุงู ูู ูุจููุฉ ุฌุฑูู ุณูุฏุฉ ุงุณููุง ุนูุงุฑุฉ ุจูุช ุณุนุฏ ุจู ุฃุณุงูุฉ ุฃู ููู ุฃู ุงุณููุง ุฌุฏุงุก ุณุนุฏ ุฃู ุญุจู ุจูุช ุฃุณุนุฏ ุจู ุนููู ุฃู ุฑูุจุฉ .\nุชุฒูุฌ ุนููู ุงูุณูุงู ูููุฑุฉ ุงูุซุงููุฉ ูู ููุนุงู ุณูุฏุฉ ุชุฏุนู ูุงูุดูุณ ุจูุช ูุถุงุถ ุจู ุนูุฑู ู ููู ุฃู ุงุณููุง ูู ุณูุฏุฉ ุจูุช ูุถุงุถ ุจู ุนูุฑู ุงูุฌุฑููู ."
  },
  {
    "number": "ุฒูุฌุฉ ุฅุณุญุงู ุนููู ุงูุณูุงู ",
    "text": "",
    "label": "ุฅุณุญุงู ุนููู ุงูุณูุงู :\nุชุฒูุฌ ุฅุณุญุงู ุนููู ุงูุณูุงู ูู ุงูุณูุฏุฉ ุฑููุฉ ุจูุช ุจุชูุฆูู ."
  },
  {
    "number": "ุฒูุฌุฉ ูุนููุจ ุนููู ุงูุณูุงู ",
    "text": "",
    "label": "ูุนููุจ ุนููู ุงูุณูุงู :\n ุชุฒูุฌ ูุนููุจ ุนููู ุงูุณูุงู ุฃุฑุจุน ูุณุงุก ูู ููุง ุฃู ูููุฉ ุจูุช ูุงุจุงู ู ุฃุฎุชูุง ุฑุงุญูู ุจูุช ูุงุจุงู ู ุฒูููุง ู ุจูููุง .                      "
  },
  {
    "number": "ุฒูุฌุฉ ููุณู ุนููู ุงูุณูุงู ",
    "text": "",
    "label": "ููุณู ุนููู ุงูุณูุงู :\n ุฐููุฑ ูู ุจุนุถ ุงูุฃุซุฑ ุฃู ููุณู ุนููู ุงูุณูุงู ุชุฒูุฌ ูู ุณูุฏุฉ ูุตุฑูุฉ ุชุฏุนู ุฃุณููุงุช ุซู ุชุฒูุฌ ุจุนุฏ ุฐูู ุจุงูุณูุฏุฉ ุฒููุฎุง ู ุงุณููุง ุฑุงุนูู ุจูุช ุฑูุงููู .                      "
  },
  {
    "number": "ุฒูุฌุฉ ุฃููุจ ุนููู ุงูุณูุงู ",
    "text": "",
    "label": "ุฃููุจ ุนููู ุงูุณูุงู :\nุชุฒูุฌ ุฃููุจ ุนููู ุงูุณูุงู ุจุงูุณูุฏุฉ ุฑุญูุฉ ุจูุช ุฃูุฑุงุฆูู ุจู ููุณู ุจู ูุนููุจ ุนูููู ุงูุณูุงู ู ููุงู ุฃู ุงุณููุง ููุง ู ูู ุญููุฏุฉ ุงููุจู ููุณู ุนููู ุงูุณูุงู ."
  },
  {
    "number": "ุฒูุฌุฉ ููุณู ุนููู ุงูุณูุงู ",
    "text": "",
    "label": "ููุณู ุนููู ุงูุณูุงู :\nุชุฒูุฌ ููุณู ุนููู ุงูุณูุงู ุฃุฑุจุน ูุฑุงุช ุงูุฃููู ูุงูุช ูู ุตููุฑุฉ ุงุจูุฉ ุงููุจู ุดุนูุจ ุนููู ุงูุณูุงู .\nุชุฒูุฌ ูููุฑุฉ ุงูุซุงููุฉ ูู ุณูุฏุฉ ุชุฏุนู ุฌุจุดูุฉ ู ููุงู ุฃู ุงุณููุง ุซุงุฑุจูุฒ ุฃู ููุดูุช ู ูู ุฃููุฑุฉ ููููุฉ ููุด ู ูู ุงููุนุฑูู ุฃู ููููุฉ ููุด ุญุงููุงู ูู ุฌุฒุก ูู ูุตุฑ ู ุงูุณูุฏุงู ุฌููุจ ุงูุณูุฏุงู .\nุงููุฑุฉ ุงูุซุงูุซุฉ ูู ุณูุฏุฉ ุชุณูู ุจูุช ูููู .\nุงููุฑุฉ ุงูุฑุงุจุนุฉ ูู ุณูุฏุฉ ุงุณููุง ุจูุช ุญุจุงุจ ."
  },
  {
    "number": "ุฒูุฌุฉ ูุงุฑูู ุนููู ุงูุณูุงู ",
    "text": "",
    "label": "ูุงุฑูู ุนููู ุงูุณูุงู : \nุชุฒูุฌ ูุงุฑูู ุนููู ุงูุณูุงู ูู ุณูุฏุฉ ููุงู ุฃู ุงุณููุง ุฅูููุฏ ู ููุงู ุฃูุถุงู ุฅููุดูุจุง ."
  },
  {
    "number": "ุฒูุฌุฉ ุฏุงููุฏ ุนููู ุงูุณูุงู ",
    "text": "",
    "label": "ุฏุงูุฏ ุนููู ุงูุณูุงู :\nุชุฒูุฌ ูุจู ุงููู ุฏุงูุฏ ุนููู ุงูุณูุงู ูู ุชุณุน ูุณุงุก ูู ุงูุฒูุฌุฉ ุงูุฃููู ูู ูููุงู ุจูุช ุดุงูู ู ูุนูุฉ ุงุจูุฉ ุชููุงู ู ูุฌูุซ ู ุฃุจูุทุงู ู ุฃุจูุฌุงุจู ุงููุฑูููุฉ ู ุนุฌูุฉ ู ุฃุฎููุนูู ุงูุจุฒุฑุนูููุฉ ุฃู ููุงู ุฃุถูููุนู ุงูุจุฒุฑุนูููุฉ ู ูููุฉ ุงุจูุฉ ุชููุงู ููู ุฌุดูุฑ ู ูุชุดูุน ุงุจูุฉ ุนูุฆูู ."
  },
  {
    "number": "ุฒูุฌุฉ ุณูููุงู ุนููู ุงูุณูุงู ",
    "text": "",
    "label": "ุณูููุงู ุนููู ุงูุณูุงู :\nุฐูุฑ ูู ุงูุชูุฑุงุฉ ุฃู ูุจู ุงููู ุณูููุงู ุนููู ุงูุณูุงู ูุงู ูุชุฒูุฌุงู ูู ุฃูู ุฃูุฑุฃุฉ .\nูููุงู ูู ุจุนุถ ุงููุตุงุฏุฑ ุฃู ูุณูุฏูุง ุณูููุงู 999 ุฒูุฌุฉ .\nููู ุฐูุฑ ูู ุงูุณูุฉ ุงููุจููุฉ ุงููุดุฑูุฉ ุฃู ูุณูุฏูุง ุณูููุงู ูุงุฆุฉ ุฒูุฌุฉ ุ ุจุฏููู ุงูุญุฏูุซ :  ุนููู ุฃูุจูู ููุฑูููุฑูุฉู ููุงูู : ููุงูู ุณูููููููุงูู ุจููู ุฏูุงููุฏู ุนูููููููููุง ุงูุณูููุงู : ูุฃูุทููููููู ุงููููููููุฉู ุจูููุงุฆูุฉู ุงููุฑูุฃูุฉู ุชูููุฏู ููููู ุงููุฑูุฃูุฉู ุบููุงููุง ููููุงุชููู ููู ุณูุจูููู ุงูููููู . ููููุงูู ูููู ุงูููููููู : ูููู ุฅููู ุดูุงุกู ุงูููููู . ูููููู ูููููู ุ ููููุณููู ููุฃูุทูุงูู ุจูููููู ูููููู ุชูููุฏู ููููููููู ุฅููุง ุงููุฑูุฃูุฉู ููุตููู ุฅูููุณูุงูู ููุงูู ุงููููุจูููู ุตููููู ุงูููููู ุนููููููู ููุณูููููู ูููู ููุงูู ุฅููู ุดูุงุกู ุงูููููู ูููู ููุญูููุซู ููููุงูู ุฃูุฑูุฌูู ููุญูุงุฌูุชููู โ.\nู ุฐูุฑุช ุจุนุถ ุงููุตุงุฏุฑ ุงูุชุงุฑูุฎูุฉ ุฃู ูู ุจูู ุฒูุฌุงุช ูุจู ุงููู ุณูููุงู ุนููู ุงูุณูุงู ุฃููุฑุฉ ูุฑุนูููุฉ ุจูุช ูุฑุนูู ูุตุฑ ู ุฃูุถุงู ูู ุฒูุฌุงุชู ุงููููุฉ ุจูููุณ ูููุฉ ููููุฉ ุณุจุฃ ."
  },
  {
    "number": "ุฒูุฌุฉ ุฒูุฑูุง ุนููู ุงูุณูุงู ",
    "text": "",
    "label": "ุฒูุฑูุง ุนููู ุงูุณูุงู :\nุชุฒูุฌ ุฒูุฑูุง ุนููู ุงูุณูุงู ูู ุงูุณูุฏุฉ ุฅูุดุงุน ุดูููุฉ ุงูุณูุฏุฉ ุญูุฉ ุจูุช ูุงููุฐ ุฒูุฌุฉ ุนูุฑุงู ู ูู ุฎุงูุฉ ุงูุณูุฏุฉ ูุฑูู ุงูุนุฐุฑุงุก ู ุงุณููุง ุฅููุตุงุจุงุช ุจุงููุบุฉ ุงููููุงููุฉ ."
  },
  {
    "number": "ุฒูุฌุฉ ูุญูู ุนููู ุงูุณูุงู ",
    "text": "",
    "label": "ูุญูู ุนููู ุงูุณูุงู :\nูุชู ูุญูู ุนููู ุงูุณูุงู ุนูู ูุฏ ุงููููุฏ ุงููุงุณุฏูู ู ูู ูุชุฒูุฌ ุจุนุฏ ."
  },
  {
    "number": "ุฒูุฌุฉ ุนูุณู ุนููู ุงูุณูุงู ",
    "text": "",
    "label": "ุนูุณู ุนููู ุงูุณูุงู :\nูู ูุชุฒูุฌ ุนูุณู ุนููู ุงูุณูุงู ุทููุฉ ุญูุงุชู ู ูุงู ุฃุญุฏ ุงูุฃูุจูุงุก ุงูุนุฒุงุจ ."
  },
  {
    "number": "ุฒูุฌุงุช ูุญูุฏ ุฑุณูู ุงููู ุตูู ุงููู ุนููู ูุณูู ",
    "text": "",
    "label": "ูุญูุฏ ุฑุณูู ุงููู (ุตูู ุงููู ุนููู ูุณูู) :\nุชุฒูุฌ ุฑุณูู ุงููู (ุต) ูู 19 ุณูุฏุฉ ูููู :\n๐ธ 12 ุณูุฏุฉ ุนูุฏ ุนูููุง ู ุฏุฎู ุจูุง .\n๐ธ 7 ูุณุงุก ุนูุฏ ุนูููู ููุท ู ูู ูุฏุฎู ุจูู .\n\nุงูุงุซูู ุนุดุฑ ุณูุฏุฉ ูู : \n๐ธ ุงูุณุจุฏุฉ ุฎุฏูุฌุฉ ุจูุช ุฎูููุฏ . \n๐ธ ุงูุณูุฏุฉ ุณูุฏุฉ ุจูุช ุฒูุนุฉ .\n๐ธ ุงูุณูุฏุฉ ุนุงุฆุดุฉ ุจูุช ุฃุจู ุจูุฑ ุงูุตุฏูู .\n๐ธ ุงูุณูุฏุฉ ุญูุตุฉ ุจูุช ุนูุฑ ุจู ุงูุฎุทุงุจ .\n๐ธ ุงูุณูุฏุฉ ุฒููุจ ุจูุช ุฎุฒููุฉ .\n๐ธ ุงูุณูุฏุฉ ุฃู ุณููุฉ .\n๐ธ ุงูุณูุฏุฉ ุฒููุจ ุจูุช ุฌุญุด .\n๐ธ ุงูุณูุฏุฉ ุฌููุฑูุฉ ุจูุช ุงูุญุงุฑุซ .\n๐ธ ุงูุณูุฏุฉ ูุงุฑูุฉ ุงููุจุทูุฉ .\n๐ธ ุงูุณูุฏุฉ ุฃู ุญุจูุจุฉ .\n๐ธ ุงูุณูุฏุฉ ุตููุฉ ุจูุช ุญูู .\n๐ธ ุงูุณูุฏุฉ ูููููุฉ  ุจูุช ุงูุญุงุฑุซ .\n\n ุงูุณุจุนุฉ ูุณุงุก ูู : \n๐ธ ุนูุฑุฉ ุงูููุงุจูุฉ .\n๐ธ ูุชููุฉ ุจูุช ููุณ .\n๐ธ ุณูุง ุงูุณูููุฉ .\n๐ธ ุดุฑุงู ุงูููุจูุฉ .\n๐ธ ุงูุนุงููุฉ ุงูููุงุจูุฉ .\n๐ธ ูููู ุงูุฃูุณูุฉ .\n๐ธ ุฃุณูุงุก ุจูุช ุงููุนูุงู ."
  }
]